garlandtools/__init__.py
garlandtools/class_garlandtools.py
garlandtools/globals.py
garlandtools/job.py
garlandtools/test_class_garlandtools.py
garlandtools/test_class_job.py
garlandtools/test_init_credits.py
garlandtools-2.0.1.dist-info/LICENSE
garlandtools-2.0.1.dist-info/METADATA
garlandtools-2.0.1.dist-info/WHEEL
garlandtools-2.0.1.dist-info/top_level.txt
garlandtools-2.0.1.dist-info/RECORD
