Metadata-Version: 2.1
Name: garlandtools
Version: 2.0.1
Summary: Python PIP module for GarlandTools
Home-page: https://github.com/Sakul6499/GarlandTools-PIP
Author: Lukas Weber
Author-email: me@sakul6499.de
License: MIT License
Classifier: Development Status :: 1 - Planning
Classifier: Intended Audience :: Science/Research
Classifier: License :: OSI Approved :: MIT License
Classifier: Operating System :: POSIX :: Linux
Classifier: Programming Language :: Python :: 3
Classifier: Programming Language :: Python :: 3.7
Classifier: Programming Language :: Python :: 3.8
Classifier: Programming Language :: Python :: 3.10
License-File: LICENSE
Requires-Dist: mpi4py >=2.0
Requires-Dist: requests-cache >=0.9
